[

  {
    "id": "pcs-001",
    "category": "Plant Care", 
    "title": "Mastering Houseplant Watering",
    "summary": "Learn the golden rules of watering to keep your plants thriving, not drowning. Covers when, how, and how much for common plant types.",
    "sourceName": "University of GoodPlants Extension",
    "contentUrl": "https://mygreenscape.ca/a/blog/post/ultimate-guide-to-indoor-plant-watering",
    "image_url": "https://blog.sfapp.magefan.top/media/mygreenscape-ca.myshopify.com/images/IMG_0452.jpeg", 
    "difficulty": "Beginner" 
  },
  {
    "id": "pcs-002",
    "category": "Plant Safety",
    "title": "Top 10 Plants Toxic to Cats & Dogs",
    "summary": "Identify common houseplants that pose a risk to your furry friends. Includes symptoms to watch for.",
    "sourceName": "ASPCA",
    "contentUrl": "https://www.aspca.org/pet-care/animal-poison-control/toxic-and-non-toxic-plants",
   
    "difficulty": "N/A"
  },
 

  {
    "id": "pcs-003",
    "category": "Plant Care",
    "title": "Decoding Light for Indoor Plants",
    "summary": "From low light to bright indirect, understand what your plants need and how to provide it in your home.",
    "sourceName": "The Spruce",
    "contentUrl": "https://www.thespruce.com/search?q=plant+care",
    "image_url": "https://www.thespruce.com/thmb/khpHeYScMMo-QTVCYlXQcW6ZLqI=/315x208/filters:no_upscale():max_bytes(150000):strip_icc():format(webp)/grow-maranta-inside-1902647-02-de777eb8e7804c3d86d658cd242583d6.jpg",
    "difficulty": "Beginner"
  }
  
]
